wet.py
libgwit/GwitParser.py
libgwit/GwitPetnames.py
libgwit/GwitSite.py
libgwit/SitesConfig.py
libgwit/common.py
wet_gwit-0.1.4.dist-info/METADATA
wet_gwit-0.1.4.dist-info/WHEEL
wet_gwit-0.1.4.dist-info/entry_points.txt
wet_gwit-0.1.4.dist-info/licenses/LICENSE
wet_gwit-0.1.4.dist-info/RECORD
