Metadata-Version: 2.4
Name: wet-gwit
Version: 0.1.4
Summary: A console client for Gwit protocol
Project-URL: homepage, https://framagit.org/matograine/wet
Project-URL: source, https://framagit.org/matograine/wet.git
Project-URL: issues, https://framagit.org/matograine/wet/-/issues
Project-URL: changelog, https://framagit.org/matograine/wet/-/blob/master/CHANGELOG.md
Author-email: Matograine <matograine@zaclys.net>
Maintainer-email: Matograine <matograine@zaclys.net>
License:                     GNU AFFERO GENERAL PUBLIC LICENSE
License-File: LICENSE
Keywords: browser,gwit,offline-first
Classifier: Development Status :: 3 - Alpha
Classifier: Environment :: Console
Classifier: License :: OSI Approved :: GNU Affero General Public License v3 or later (AGPLv3+)
Classifier: Operating System :: OS Independent
Classifier: Programming Language :: Python :: 3 :: Only
Classifier: Topic :: Communications
Classifier: Topic :: Internet
Requires-Python: >=3.7
Requires-Dist: gitpython
Requires-Dist: python-gnupg
